Scraping/__init__.py
Scraping/scraping_P.py
Scraping_Perlverity_Python/__init__.py
Scraping_Perlverity_Python/scraping_P.py
Scraping_Perlverity_Python-1.0.2.dist-info/METADATA
Scraping_Perlverity_Python-1.0.2.dist-info/WHEEL
Scraping_Perlverity_Python-1.0.2.dist-info/top_level.txt
Scraping_Perlverity_Python-1.0.2.dist-info/RECORD
