Metadata-Version: 2.1
Name: Scraping-Perlverity-Python
Version: 1.0.2
Summary: pip install Success!! pip install でライブラリインストールでWebスクレイピング起動可能。
Home-page: https://github.com/Perlverity/Python_Scraping_pip_install
Author: Perlverity
Author-email: perlverity@gmail.com
License: MIT
Keywords: sample setuptools development
Platform: UNKNOWN
Classifier: Programming Language :: Python :: 3.6
Requires-Dist: requests (>=2.14.2)
